pathcfd/__init__.py
pathcfd-0.1.dist-info/LICENSE.txt
pathcfd-0.1.dist-info/METADATA
pathcfd-0.1.dist-info/WHEEL
pathcfd-0.1.dist-info/top_level.txt
pathcfd-0.1.dist-info/RECORD
