Metadata-Version: 2.1
Name: pathcfd
Version: 0.1
Summary: it changes local the given path to panda uplodable path
Home-page: UNKNOWN
Author: sandeep
Author-email: shirolesandeep@rediffmail.com
License: UNKNOWN
Platform: UNKNOWN
License-File: LICENSE.txt
